salaga/__init__.py
salaga/clusterOp/__init__.py
salaga/clusterOp/salagaDaemon.py
salaga/utils/__init__.py
salaga/utils/hashCodeGen.py
salaga/utils/localMan.py
salaga/utils/neighbour.py
salaga/utils/slgcodes.py
salaga-0.0.1a5.dist-info/LICENSE
salaga-0.0.1a5.dist-info/METADATA
salaga-0.0.1a5.dist-info/WHEEL
salaga-0.0.1a5.dist-info/top_level.txt
salaga-0.0.1a5.dist-info/RECORD
